{
  "@id": "dtmi:CloudRail:IOL:V310:D707;1",
  "@type": "Interface",
  "@context": "dtmi:dtdl:context;2",
  "displayName": "TN2xx3",
  "description": "Electronic temperature sensor, -58...302 °F, Length 30 mm, IO-Link, Process connection 1/2'' NPT",
  "contents": [
    {
      "@type": [
        "Telemetry",
        "Temperature"
      ],
      "name": "Temperature_C",
      "displayName": "Temperature_C",
      "schema": "double",
      "unit": "degreeCelsius"
    },
    {
      "@type": [
        "Telemetry",
        "Temperature"
      ],
      "name": "Temperature_F",
      "displayName": "Temperature_F",
      "schema": "double",
      "unit": "degreeFahrenheit"
    },
    {
      "@type": "Telemetry",
      "name": "OUT2",
      "displayName": "OUT2",
      "schema": "dtmi:CloudRail:IOL:V310:D707:OUT;1"
    },
    {
      "@type": "Telemetry",
      "name": "OUT1",
      "displayName": "OUT1",
      "schema": "dtmi:CloudRail:IOL:V310:D707:OUT;1"
    }
  ],
  "schemas": [
    {
      "@id": "dtmi:CloudRail:IOL:V310:D707:OUT;1",
      "@type": "Enum",
      "valueSchema": "string",
      "enumValues": [
        {
          "name": "Inactive",
          "enumValue": "Inactive"
        },
        {
          "name": "Active",
          "enumValue": "Active"
        }
      ]
    }
  ]
}