{
  "@context": "dtmi:dtdl:context;2",
  "@id": "dtmi:benq:product:ops_tey21_series;1",
  "@type": "Interface",
  "displayName": "BenQ OPS TEY21 Series",
  "description": "BenQ OPS TEY21 Series capability model.",
  "contents": [
    {
      "@type": "Component",
      "name": "deviceInfo",
      "schema": "dtmi:azure:DeviceManagement:DeviceInformation;1",
      "displayName": "Device Information interface",
      "description": "Interface of basic device hardware information."
    },
    {
      "@type": "Component",
      "name": "runtimeInfo",
      "schema": "dtmi:benq:product:runtimeInfo;1",
      "displayName": "Runtime Information interface",
      "description": "Interface of runtime information."
    }
  ]
}